prog_models/__init__.py
prog_models/composite_model.py
prog_models/ensemble_model.py
prog_models/exceptions.py
prog_models/linear_model.py
prog_models/prognostics_model.py
prog_models/sim_result.py
prog_models/visualize.py
prog_models/data_models/__init__.py
prog_models/data_models/data_model.py
prog_models/data_models/dmd.py
prog_models/data_models/lstm_model.py
prog_models/data_models/pce.py
prog_models/datasets/__init__.py
prog_models/datasets/nasa_battery.py
prog_models/datasets/nasa_cmapss.py
prog_models/loading/__init__.py
prog_models/loading/controllers.py
prog_models/loading/gaussian_wrapper.py
prog_models/loading/moving_average.py
prog_models/loading/piecewise.py
prog_models/models/__init__.py
prog_models/models/battery_circuit.py
prog_models/models/battery_electrochem.py
prog_models/models/centrifugal_pump.py
prog_models/models/dcmotor.py
prog_models/models/dcmotor_singlephase.py
prog_models/models/esc.py
prog_models/models/pneumatic_valve.py
prog_models/models/powertrain.py
prog_models/models/propeller_load.py
prog_models/models/thrown_object.py
prog_models/models/aircraft_model/__init__.py
prog_models/models/aircraft_model/aircraft.py
prog_models/models/aircraft_model/small_rotorcraft.py
prog_models/models/aircraft_model/vehicles/__init__.py
prog_models/models/aircraft_model/vehicles/vehicles.py
prog_models/models/aircraft_model/vehicles/aero/__init__.py
prog_models/models/aircraft_model/vehicles/aero/aerodynamics.py
prog_models/models/aircraft_model/vehicles/control/__init__.py
prog_models/models/aircraft_model/vehicles/control/allocation_functions.py
prog_models/models/experimental/__init__.py
prog_models/models/experimental/paris_law.py
prog_models/models/test_models/__init__.py
prog_models/models/test_models/linear_models.py
prog_models/models/test_models/linear_thrown_object.py
prog_models/utils/__init__.py
prog_models/utils/calc_error.py
prog_models/utils/containers.py
prog_models/utils/input_validation.py
prog_models/utils/next_state.py
prog_models-1.5.2.dist-info/METADATA
prog_models-1.5.2.dist-info/WHEEL
prog_models-1.5.2.dist-info/top_level.txt
prog_models-1.5.2.dist-info/RECORD
