Metadata-Version: 2.1
Name: prog-models
Version: 1.5.2
Summary: The NASA Prognostic Model Package is a python modeling framework focused on defining and building models for prognostics (computation of remaining useful life) of engineering systems, and provides a set of prognostics models for select components developed within this framework, suitable for use in prognostics applications for these components.
Home-page: https://nasa.github.io/progpy/prog_models_guide.html
Author: Christopher Teubert
Author-email: christopher.a.teubert@nasa.gov
License: NOSA
Project-URL: Bug Reports, https://github.com/nasa/prog_models/issues
Project-URL: Docs, https://nasa.github.io/progpy/prog_models_guide.html
Project-URL: Organization, https://www.nasa.gov/content/diagnostics-prognostics
Project-URL: Source, https://github.com/nasa/prog_models
Keywords: prognostics,diagnostics,fault detection,fdir,physics modeling,prognostics and health management,PHM,health management,surrogate modeling,model tuning,simulation,ivhm
Classifier: Development Status :: 5 - Production/Stable
Classifier: Intended Audience :: Science/Research
Classifier: Intended Audience :: Developers
Classifier: Intended Audience :: Manufacturing
Classifier: Topic :: Scientific/Engineering
Classifier: Topic :: Scientific/Engineering :: Artificial Intelligence
Classifier: Topic :: Scientific/Engineering :: Physics
Classifier: License :: Other/Proprietary License 
Classifier: Programming Language :: Python :: 3
Classifier: Programming Language :: Python :: 3.7
Classifier: Programming Language :: Python :: 3.8
Classifier: Programming Language :: Python :: 3.9
Classifier: Programming Language :: Python :: 3.10
Classifier: Programming Language :: Python :: 3.11
Classifier: Programming Language :: Python :: 3 :: Only
Requires-Python: >=3.7, <3.12
Requires-Dist: scipy
Requires-Dist: pandas
Requires-Dist: matplotlib
Requires-Dist: requests
Requires-Dist: chaospy
Requires-Dist: fastdtw
Requires-Dist: tensorflow ; platform_system != "Darwin" or platform_machine != "arm64"
Requires-Dist: tensorflow-macos ; platform_system == "Darwin" and platform_machine == "arm64"
